soapboxslide.py
soapboxslide-1.0.2.dist-info/licenses/LICENSE
soapboxslide-1.0.2.dist-info/METADATA
soapboxslide-1.0.2.dist-info/WHEEL
soapboxslide-1.0.2.dist-info/top_level.txt
soapboxslide-1.0.2.dist-info/RECORD
