Metadata-Version: 2.4
Name: soapboxslide
Version: 1.0.2
Summary: A Computational Soap Box Slide
Author-email: Toon Verstraelen <toon.verstraelen@ugent.be>
License-Expression: GPL-3.0-or-later
Project-URL: Documentation, https://github.com/molmod/soapboxslide/
Project-URL: Issues, https://github.com/molmod/soapboxslide/issues
Project-URL: Source, https://github.com/molmod/soapboxslide/
Project-URL: Changelog, https://github.com/molmod/soapboxslide/blob/main/CHANGELOG.md
Classifier: Development Status :: 4 - Beta
Classifier: Environment :: Console
Classifier: Intended Audience :: Education
Classifier: Operating System :: POSIX
Classifier: Programming Language :: Python :: 3
Classifier: Programming Language :: Python :: 3.11
Classifier: Programming Language :: Python :: 3.12
Classifier: Programming Language :: Python :: 3.13
Classifier: Programming Language :: Python :: 3.14
Classifier: Topic :: Scientific/Engineering :: Physics
Requires-Python: >=3.11
License-File: LICENSE
Requires-Dist: attrs>=24.2.0
Requires-Dist: cattrs>=24.1.1
Requires-Dist: numpy>=2.3.1
Requires-Dist: scipy>=1.16.0
Requires-Dist: matplotlib>=3.10.3
Dynamic: license-file
